mini project - 3 bit UpDown counter/UpDown counter with seperate modules/down.v
module down_counter(Q, clk, enable);
    input clk, enable;
    output reg [2:0] Q;

    initial begin
        Q = 3'b111;  
    end

    always @(posedge clk) begin
        if (enable) begin
            Q <= Q - 1;  
        end
    end
endmodule

mini project - 3 bit UpDown counter/UpDown counter with seperate modules/up.v
module up_counter(Q, clk, enable);
    input clk, enable;
    output reg [2:0] Q;

    initial begin
        Q = 3'b000;  
    end

    always @(posedge clk) begin
        if (enable) begin
            Q <= Q + 1;  
        end
    end
endmodule

mini project - 3 bit UpDown counter/UpDown counter with seperate modules/Up_down_tb.v
`timescale 1ns / 1ps

module tb_up_down_counter;

reg clk;
reg enable_up, enable_down;

wire [2:0] Q_up;
wire [2:0] Q_down;

up_counter uut_up (
    .Q(Q_up),
    .clk(clk),
    .enable(enable_up)
);

down_counter uut_down (
    .Q(Q_down),
    .clk(clk),
    .enable(enable_down)
);

initial begin
    clk = 0;
    forever #5 clk = ~clk;  
end

initial begin
    enable_up = 1;
    enable_down = 0;  
    #80;  
    
    enable_up = 0;
    enable_down = 1;
    $display("Switching to Down Counter phase: ");
    
    #80;
    
    $finish;
end

initial begin
    forever begin
        @(posedge clk);  
        if (enable_up) begin
            $display("Up Counter phase: At time %t: clk = %b, Q_up = %b", $time, clk, Q_up);
        end else if (enable_down) begin
            $display("Down Counter phase: At time %t: clk = %b, Q_down = %b", $time, clk, Q_down);
        end
    end
end

initial begin
    $dumpfile("up_down_counter.vcd"); 
    $dumpvars(0, tb_up_down_counter); 
end

endmodule

mini project - 3 bit UpDown counter/UpDown counter with seperate modules/up_down_counter.vcd
$date
	Tue Nov 12 08:23:54 2024
$end
$version
	Icarus Verilog
$end
$timescale
	1ps
$end
$scope module tb_up_down_counter $end
$var wire 3 ! Q_up [2:0] $end
$var wire 3 " Q_down [2:0] $end
$var reg 1 # clk $end
$var reg 1 $ enable_down $end
$var reg 1 % enable_up $end
$scope module uut_down $end
$var wire 1 # clk $end
$var wire 1 $ enable $end
$var reg 3 & Q [2:0] $end
$upscope $end
$scope module uut_up $end
$var wire 1 # clk $end
$var wire 1 % enable $end
$var reg 3 ' Q [2:0] $end
$upscope $end
$upscope $end
$enddefinitions $end
#0
$dumpvars
b0 '
b111 &
1%
0$
0#
b111 "
b0 !
$end
#5000
b1 !
b1 '
1#
#10000
0#
#15000
b10 !
b10 '
1#
#20000
0#
#25000
b11 !
b11 '
1#
#30000
0#
#35000
b100 !
b100 '
1#
#40000
0#
#45000
b101 !
b101 '
1#
#50000
0#
#55000
b110 !
b110 '
1#
#60000
0#
#65000
b111 !
b111 '
1#
#70000
0#
#75000
b0 !
b0 '
1#
#80000
0#
1$
0%
#85000
b110 "
b110 &
1#
#90000
0#
#95000
b101 "
b101 &
1#
#100000
0#
#105000
b100 "
b100 &
1#
#110000
0#
#115000
b11 "
b11 &
1#
#120000
0#
#125000
b10 "
b10 &
1#
#130000
0#
#135000
b1 "
b1 &
1#
#140000
0#
#145000
b0 "
b0 &
1#
#150000
0#
#155000
b111 "
b111 &
1#
