mini project - 3 bit UpDown counter/UpDown.v
// 3-bit Up-Down Counter
module up_down_counter(Q, clk, up_down);
    input clk, up_down;
    output reg [2:0] Q;

    initial begin
        Q = 3'b000;  // Initialize counter to zero
    end

    always @(posedge clk) begin
        if (up_down) begin
            Q <= Q + 1;  // Count up
        end else begin
            Q <= Q - 1;  // Count down
        end
    end
endmodule

mini project - 3 bit UpDown counter/UpDown_tb.v
`timescale 1ns / 1ps

module tb_up_down_counter;

// Inputs
reg clk;
reg up_down;

// Outputs
wire [2:0] Q;

// Instantiate the Unit Under Test (UUT)
up_down_counter uut (
    .Q(Q),
    .clk(clk),
    .up_down(up_down)
);

// Clock Generation: Toggle every 10 ns
initial begin
    clk = 0;
    forever #5 clk = ~clk;  // Toggle clock every 5 ns (10 ns period)
end

// Test stimulus
initial begin
    // Initialize Inputs
    up_down = 1; // Start by counting up

    // Print the state every clock cycle
    forever begin
        @(posedge clk);  // Wait for the rising edge of clk
        $display("At time %t: clk = %b, up_down = %b, Q = %b", $time, clk, up_down, Q);
    end
end

// Additional stimulus
initial begin
    // Run for some time with 'up_down = 1' (UP)
    #80;  // Run for 80 ns (8 clock cycles)
    
    // Change to 'up_down = 0' (DOWN)
    up_down = 0;

    // Run for another 80 ns (8 clock cycles)
    #80;

    // Finish the simulation
    $finish;
end

// Generate VCD file for GTKWave
initial begin
    $dumpfile("up_down_counter.vcd"); // VCD output file
    $dumpvars(0, tb_up_down_counter);  // Dump all variables
end

endmodule

mini project - 3 bit UpDown counter/up_down_counter.vcd
$date
	Mon Nov 11 15:54:36 2024
$end
$version
	Icarus Verilog
$end
$timescale
	1ps
$end
$scope module tb_up_down_counter $end
$var wire 3 ! Q [2:0] $end
$var reg 1 " clk $end
$var reg 1 # up_down $end
$scope module uut $end
$var wire 1 " clk $end
$var wire 1 # up_down $end
$var reg 3 $ Q [2:0] $end
$upscope $end
$upscope $end
$enddefinitions $end
#0
$dumpvars
b0 $
1#
0"
b0 !
$end
#5000
b1 !
b1 $
1"
#10000
0"
#15000
b10 !
b10 $
1"
#20000
0"
#25000
b11 !
b11 $
1"
#30000
0"
#35000
b100 !
b100 $
1"
#40000
0"
#45000
b101 !
b101 $
1"
#50000
0"
#55000
b110 !
b110 $
1"
#60000
0"
#65000
b111 !
b111 $
1"
#70000
0"
#75000
b0 !
b0 $
1"
#80000
0"
0#
#85000
b111 !
b111 $
1"
#90000
0"
#95000
b110 !
b110 $
1"
#100000
0"
#105000
b101 !
b101 $
1"
#110000
0"
#115000
b100 !
b100 $
1"
#120000
0"
#125000
b11 !
b11 $
1"
#130000
0"
#135000
b10 !
b10 $
1"
#140000
0"
#145000
b1 !
b1 $
1"
#150000
0"
#155000
b0 !
b0 $
1"
