week 3/fullAdder.v
module andgate (y, a, b);  
input a, b;
output y;
assign y = a & b;
endmodule

module orgate (y, a, b);  
input a, b;
output y;
assign y = a | b;
endmodule

module xorgate(y, a, b);
input a, b;
output y;
assign y = a ^ b;
endmodule

module halfadder(sum, carry, A, B);
input A, B;
output sum, carry;
xorgate X1(.y(sum), .a(A), .b(B));   // sum = A ^ B
andgate A1(.y(carry), .a(A), .b(B)); // carry = A & B
endmodule

module fulladder(sum, carry, A, B, C);
input A, B, C;
output sum, carry;
wire W1, W2, C1;
halfadder HA1(.sum(W1), .carry(W2), .A(A), .B(B)); // First half-adder
halfadder HA2(.sum(sum), .carry(C1), .A(W1), .B(C)); // Second half-adder
orgate OG(.y(carry), .a(W2), .b(C1));  // OR gate 
endmodule

week 3/fullAdder_tb.v
module fulladder_tb;
reg A, B, C;
wire sum, carry;

fulladder M1(.sum(sum), .carry(carry), .A(A), .B(B), .C(C));

initial begin
#0 A = 1'b0; B = 1'b0; C = 1'b0;
#20 A = 1'b0; B = 1'b1; C = 1'b0;
#20 A = 1'b1; B = 1'b0; C = 1'b0;
#20 A = 1'b1; B = 1'b1; C = 1'b0;
#20 A = 1'b0; B = 1'b0; C = 1'b1;
#20 A = 1'b0; B = 1'b1; C = 1'b1;
#20 A = 1'b1; B = 1'b0; C = 1'b1;
#20 A = 1'b1; B = 1'b1; C = 1'b1;
end

initial begin
    $monitor($time, " A=%b, B=%b, C=%b, sum=%b, carry=%b", A, B, C, sum, carry);
end

initial begin
    $dumpfile("fulladder.vcd");
    $dumpvars(0, fulladder_tb);
end

endmodule

week 3/fulladder.vcd
$date
	Fri Aug 23 14:52:25 2024
$end
$version
	Icarus Verilog
$end
$timescale
	1s
$end
$scope module fulladder_tb $end
$var wire 1 ! sum $end
$var wire 1 " carry $end
$var reg 1 # A $end
$var reg 1 $ B $end
$var reg 1 % C $end
$scope module M1 $end
$var wire 1 # A $end
$var wire 1 $ B $end
$var wire 1 % C $end
$var wire 1 ! sum $end
$var wire 1 " carry $end
$var wire 1 & W2 $end
$var wire 1 ' W1 $end
$var wire 1 ( C1 $end
$scope module HA1 $end
$var wire 1 # A $end
$var wire 1 $ B $end
$var wire 1 ' sum $end
$var wire 1 & carry $end
$scope module A1 $end
$var wire 1 # a $end
$var wire 1 $ b $end
$var wire 1 & y $end
$upscope $end
$scope module X1 $end
$var wire 1 # a $end
$var wire 1 $ b $end
$var wire 1 ' y $end
$upscope $end
$upscope $end
$scope module HA2 $end
$var wire 1 ' A $end
$var wire 1 % B $end
$var wire 1 ! sum $end
$var wire 1 ( carry $end
$scope module A1 $end
$var wire 1 ' a $end
$var wire 1 % b $end
$var wire 1 ( y $end
$upscope $end
$scope module X1 $end
$var wire 1 ' a $end
$var wire 1 % b $end
$var wire 1 ! y $end
$upscope $end
$upscope $end
$scope module OG $end
$var wire 1 & a $end
$var wire 1 ( b $end
$var wire 1 " y $end
$upscope $end
$upscope $end
$upscope $end
$enddefinitions $end
#0
$dumpvars
0(
0'
0&
0%
0$
0#
0"
0!
$end
#20
1!
1'
1$
#40
0$
1#
#60
1"
0!
1&
0'
1$
#80
0"
1!
0&
1%
0$
0#
#100
1"
1(
0!
1'
1$
#120
0$
1#
#140
0(
1!
1&
0'
1$
