wk reg without alu/reg.v
module dfrl_16 (
    input wire clk,
    input wire reset,
    input wire load,
    input wire [15:0] in,
    output reg [15:0] out
);
    always @(posedge clk or posedge reset) begin
        if (reset) begin
            out <= 16'b0; // Reset the output to zero
        end else if (load) begin
            out <= in; // Load input to output
        end
    end
endmodule

module reg_file (
    input wire clk,
    input wire reset,
    input wire wr, // Write enable
    input wire [2:0] rd_addr_a, // Read address A
    input wire [2:0] rd_addr_b, // Read address B
    input wire [2:0] wr_addr, // Write address
    input wire [15:0] d_in, // Data input
    output wire [15:0] d_out_a, // Data output A
    output wire [15:0] d_out_b // Data output B
);
    wire [15:0] dout[7:0]; // Internal outputs for 8 registers
    wire [7:0] load; // Load signals for each register

    // Instantiate 8 registers (dfrl_16)
    dfrl_16 dfrl_16_0(clk, reset, load[0], d_in, dout[0]);
    dfrl_16 dfrl_16_1(clk, reset, load[1], d_in, dout[1]);
    dfrl_16 dfrl_16_2(clk, reset, load[2], d_in, dout[2]);
    dfrl_16 dfrl_16_3(clk, reset, load[3], d_in, dout[3]);
    dfrl_16 dfrl_16_4(clk, reset, load[4], d_in, dout[4]);
    dfrl_16 dfrl_16_5(clk, reset, load[5], d_in, dout[5]);
    dfrl_16 dfrl_16_6(clk, reset, load[6], d_in, dout[6]);
    dfrl_16 dfrl_16_7(clk, reset, load[7], d_in, dout[7]);

    // Generate load signals based on the write address
    assign load = {8{wr}} & (1 << wr_addr);

    // Multiplexers to read data from the selected registers
    assign d_out_a = (rd_addr_a == 3'd0) ? dout[0] :
                     (rd_addr_a == 3'd1) ? dout[1] :
                     (rd_addr_a == 3'd2) ? dout[2] :
                     (rd_addr_a == 3'd3) ? dout[3] :
                     (rd_addr_a == 3'd4) ? dout[4] :
                     (rd_addr_a == 3'd5) ? dout[5] :
                     (rd_addr_a == 3'd6) ? dout[6] :
                     (rd_addr_a == 3'd7) ? dout[7] : 16'b0;

    assign d_out_b = (rd_addr_b == 3'd0) ? dout[0] :
                     (rd_addr_b == 3'd1) ? dout[1] :
                     (rd_addr_b == 3'd2) ? dout[2] :
                     (rd_addr_b == 3'd3) ? dout[3] :
                     (rd_addr_b == 3'd4) ? dout[4] :
                     (rd_addr_b == 3'd5) ? dout[5] :
                     (rd_addr_b == 3'd6) ? dout[6] :
                     (rd_addr_b == 3'd7) ? dout[7] : 16'b0;
endmodule

wk reg without alu/reg_tb.v
`timescale 1ns / 1ps

module tb_reg_file; // Testbench module

    // Inputs
    reg clk;
    reg reset;
    reg wr; // Write enable
    reg [2:0] rd_addr_a; // Read address A
    reg [2:0] rd_addr_b; // Read address B
    reg [2:0] wr_addr; // Write address
    reg [15:0] d_in; // Data input

    // Outputs
    wire [15:0] d_out_a; // Data output A
    wire [15:0] d_out_b; // Data output B

    // Instantiate the reg_file
    reg_file uut (
        .clk(clk),
        .reset(reset),
        .wr(wr),
        .rd_addr_a(rd_addr_a),
        .rd_addr_b(rd_addr_b),
        .wr_addr(wr_addr),
        .d_in(d_in),
        .d_out_a(d_out_a),
        .d_out_b(d_out_b)
    );

    // Clock generation
    initial begin
        clk = 0;
        forever #5 clk = ~clk; // 10 ns clock period
    end

    // Test procedure
    initial begin
        // Initialize inputs
        reset = 1;
        wr = 0;
        rd_addr_a = 3'd0;
        rd_addr_b = 3'd0;
        wr_addr = 3'd0;
        d_in = 16'b0;

        // Wait for some time and release reset
        #10;
        reset = 0;

        // Write data to register 0
        wr = 1;
        wr_addr = 3'd0;
        d_in = 16'hABCD; // Sample data
        #10; // Wait for one clock cycle
        wr = 0;

        // Read from register 0
        rd_addr_a = 3'd0; // Select register 0
        rd_addr_b = 3'd1; // Select register 1 (should be 0)
        #10;

        // Write data to register 1
        wr = 1;
        wr_addr = 3'd1;
        d_in = 16'h1234; // Sample data
        #10; // Wait for one clock cycle
        wr = 0;

        // Read from both registers
        rd_addr_a = 3'd0; // Select register 0
        rd_addr_b = 3'd1; // Select register 1
        #10;

        // Write data to register 2
        wr = 1;
        wr_addr = 3'd2;
        d_in = 16'h5678; // Sample data
        #10; // Wait for one clock cycle
        wr = 0;

        // Read from all three registers
        rd_addr_a = 3'd2; // Select register 2
        rd_addr_b = 3'd0; // Select register 0
        #10;

        // Check if reset works
        reset = 1; // Assert reset
        #10;
        reset = 0; // Release reset

        // Read from register 0 (should be 0 after reset)
        rd_addr_a = 3'd0;
        rd_addr_b = 3'd1; // Select register 1
        #10;

        // Finish the simulation
        $finish;
    end

    // Monitor outputs
    initial begin
        $monitor("Time: %0dns | rd_addr_a: %0d, d_out_a: %h | rd_addr_b: %0d, d_out_b: %h",
                 $time, rd_addr_a, d_out_a, rd_addr_b, d_out_b);
    end

    // VCD file generation
    initial begin
        $dumpfile("reg_file_tb.vcd"); // Specify VCD file name
        $dumpvars(0, tb_reg_file); // Dump all variables in the testbench
    end

endmodule

wk reg without alu/reg_file_tb.vcd
$date
	Thu Oct 17 15:12:55 2024
$end
$version
	Icarus Verilog
$end
$timescale
	1ps
$end
$scope module tb_reg_file $end
$var wire 16 ! d_out_b [15:0] $end
$var wire 16 " d_out_a [15:0] $end
$var reg 1 # clk $end
$var reg 16 $ d_in [15:0] $end
$var reg 3 % rd_addr_a [2:0] $end
$var reg 3 & rd_addr_b [2:0] $end
$var reg 1 ' reset $end
$var reg 1 ( wr $end
$var reg 3 ) wr_addr [2:0] $end
$scope module uut $end
$var wire 1 # clk $end
$var wire 16 * d_in [15:0] $end
$var wire 8 + load [7:0] $end
$var wire 3 , rd_addr_a [2:0] $end
$var wire 3 - rd_addr_b [2:0] $end
$var wire 1 ' reset $end
$var wire 1 ( wr $end
$var wire 3 . wr_addr [2:0] $end
$var wire 16 / d_out_b [15:0] $end
$var wire 16 0 d_out_a [15:0] $end
$scope module dfrl_16_0 $end
$var wire 1 # clk $end
$var wire 16 1 in [15:0] $end
$var wire 1 2 load $end
$var wire 1 ' reset $end
$var reg 16 3 out [15:0] $end
$upscope $end
$scope module dfrl_16_1 $end
$var wire 1 # clk $end
$var wire 16 4 in [15:0] $end
$var wire 1 5 load $end
$var wire 1 ' reset $end
$var reg 16 6 out [15:0] $end
$upscope $end
$scope module dfrl_16_2 $end
$var wire 1 # clk $end
$var wire 16 7 in [15:0] $end
$var wire 1 8 load $end
$var wire 1 ' reset $end
$var reg 16 9 out [15:0] $end
$upscope $end
$scope module dfrl_16_3 $end
$var wire 1 # clk $end
$var wire 16 : in [15:0] $end
$var wire 1 ; load $end
$var wire 1 ' reset $end
$var reg 16 < out [15:0] $end
$upscope $end
$scope module dfrl_16_4 $end
$var wire 1 # clk $end
$var wire 16 = in [15:0] $end
$var wire 1 > load $end
$var wire 1 ' reset $end
$var reg 16 ? out [15:0] $end
$upscope $end
$scope module dfrl_16_5 $end
$var wire 1 # clk $end
$var wire 16 @ in [15:0] $end
$var wire 1 A load $end
$var wire 1 ' reset $end
$var reg 16 B out [15:0] $end
$upscope $end
$scope module dfrl_16_6 $end
$var wire 1 # clk $end
$var wire 16 C in [15:0] $end
$var wire 1 D load $end
$var wire 1 ' reset $end
$var reg 16 E out [15:0] $end
$upscope $end
$scope module dfrl_16_7 $end
$var wire 1 # clk $end
$var wire 16 F in [15:0] $end
$var wire 1 G load $end
$var wire 1 ' reset $end
$var reg 16 H out [15:0] $end
$upscope $end
$upscope $end
$upscope $end
$enddefinitions $end
#0
$dumpvars
b0 H
0G
b0 F
b0 E
0D
b0 C
b0 B
0A
b0 @
b0 ?
0>
b0 =
b0 <
0;
b0 :
b0 9
08
b0 7
b0 6
05
b0 4
b0 3
02
b0 1
b0 0
b0 /
b0 .
b0 -
b0 ,
b0 +
b0 *
b0 )
0(
1'
b0 &
b0 %
b0 $
0#
b0 "
b0 !
$end
#5000
1#
#10000
12
b1 +
0#
b1010101111001101 $
b1010101111001101 *
b1010101111001101 1
b1010101111001101 4
b1010101111001101 7
b1010101111001101 :
b1010101111001101 =
b1010101111001101 @
b1010101111001101 C
b1010101111001101 F
1(
0'
#15000
b1010101111001101 !
b1010101111001101 /
b1010101111001101 "
b1010101111001101 0
b1010101111001101 3
1#
#20000
02
b0 !
b0 /
b0 +
0#
b1 &
b1 -
0(
#25000
1#
#30000
15
b10 +
0#
b1001000110100 $
b1001000110100 *
b1001000110100 1
b1001000110100 4
b1001000110100 7
b1001000110100 :
b1001000110100 =
b1001000110100 @
b1001000110100 C
b1001000110100 F
b1 )
b1 .
1(
#35000
b1001000110100 !
b1001000110100 /
b1001000110100 6
1#
#40000
05
b0 +
0#
0(
#45000
1#
#50000
18
b100 +
0#
b101011001111000 $
b101011001111000 *
b101011001111000 1
b101011001111000 4
b101011001111000 7
b101011001111000 :
b101011001111000 =
b101011001111000 @
b101011001111000 C
b101011001111000 F
b10 )
b10 .
1(
#55000
b101011001111000 9
1#
#60000
08
b1010101111001101 !
b1010101111001101 /
b101011001111000 "
b101011001111000 0
b0 +
0#
b0 &
b0 -
b10 %
b10 ,
0(
#65000
1#
#70000
b0 "
b0 0
b0 !
b0 /
b0 3
b0 6
b0 9
0#
1'
#75000
1#
#80000
0#
b1 &
b1 -
b0 %
b0 ,
0'
