Hackathon/processor.v
module ALU (
    input [7:0] A,           
    input [7:0] B,           
    input [1:0] opcode,      
    output reg [7:0] result  
);
    always @(*) begin
        case (opcode)
            2'b00: result = A & B;  
            2'b01: result = A | B;  
            2'b10: result = ~(A & B); 
            2'b11: result = ~(A | B); 
            default: result = 8'b00000000; 
        endcase
    end
endmodule

module RegisterFile (
    input clk,                
    input [2:0] write_addr,   
    input [7:0] write_data,   
    input write_enable,       
    input [2:0] read_addr,    
    output reg [7:0] read_data
);
    reg [7:0] registers [0:7];

    always @(posedge clk) begin
        if (write_enable) begin
            registers[write_addr] <= write_data; 
        end
    end

    always @(*) begin
        read_data = registers[read_addr]; 
    end
endmodule

module Processor (
    input clk,                
    input [7:0] A,            
    input [7:0] B,            
    input [1:0] opcode,       
    input [2:0] write_addr,   
    input write_enable,       
    input [2:0] read_addr,    
    output [7:0] read_data    
);
    wire [7:0] alu_result;    

    ALU alu (
        .A(A),
        .B(B),
        .opcode(opcode),
        .result(alu_result)
    );

    RegisterFile reg_file (
        .clk(clk),
        .write_addr(write_addr),
        .write_data(alu_result),
        .write_enable(write_enable),
        .read_addr(read_addr),
        .read_data(read_data)
    );
endmodule

Hackathon/processor_tb.v
module Testbench;reg clk;reg [7:0] A;reg [7:0] B;reg [1:0] opcode;reg [2:0] write_addr;reg write_enable;reg [2:0] read_addr;wire [7:0] read_data;

    Processor uut (.clk(clk),.A(A),.B(B),.opcode(opcode),.write_addr(write_addr),.write_enable(write_enable),.read_addr(read_addr),.read_data(read_data)
    );

    initial begin
        clk = 0;
        forever #5 clk = ~clk; 
    end

    initial begin
        $dumpfile("processor_tb.vcd"); 
        $dumpvars(0, Testbench); 
    end

    initial begin
        A = 8'b11001100; B = 8'b10101010; opcode = 2'b00; 
        write_addr = 3'b000; write_enable = 1; read_addr = 3'b000;
        #10; 
        write_enable = 0; 
        #10; 
        $display("Inputs: A = %b, B = %b, Opcode = %b", A, B, opcode); 
        $display("AND Result: %b", read_data); 

        A = 8'b11001100; B = 8'b10101010; opcode = 2'b01; 
        write_addr = 3'b001; write_enable = 1; read_addr = 3'b001;
        #10; 
        write_enable = 0; 
        #10; 
        $display("Inputs: A = %b, B = %b, Opcode = %b", A, B, opcode); 
        $display("OR Result: %b", read_data); 

        A = 8'b11001100; B = 8'b10101010; opcode = 2'b10; 
        write_addr = 3'b010; write_enable = 1; read_addr = 3'b010;
        #10; 
        write_enable = 0; 
        #10; 
        $display("Inputs: A = %b, B = %b, Opcode = %b", A, B, opcode); 
        $display("NAND Result: %b", read_data); 

        A = 8'b11001100; B = 8'b10101010; opcode = 2'b11; 
        write_addr = 3'b011; write_enable = 1; read_addr = 3'b011;
        #10; 
        write_enable = 0; 
        #10; 
        $display("Inputs: A = %b, B = %b, Opcode = %b", A, B, opcode); 
        $display("NOR Result: %b", read_data); 

        #10; 
        $finish; 
    end
endmodule

Hackathon/processor_tb.vcd
$date
	Wed Nov 20 15:18:52 2024
$end
$version
	Icarus Verilog
$end
$timescale
	1s
$end
$scope module Testbench $end
$var wire 8 ! read_data [7:0] $end
$var reg 8 " A [7:0] $end
$var reg 8 # B [7:0] $end
$var reg 1 $ clk $end
$var reg 2 % opcode [1:0] $end
$var reg 3 & read_addr [2:0] $end
$var reg 3 ' write_addr [2:0] $end
$var reg 1 ( write_enable $end
$scope module uut $end
$var wire 8 ) A [7:0] $end
$var wire 8 * B [7:0] $end
$var wire 1 $ clk $end
$var wire 2 + opcode [1:0] $end
$var wire 3 , read_addr [2:0] $end
$var wire 3 - write_addr [2:0] $end
$var wire 1 ( write_enable $end
$var wire 8 . read_data [7:0] $end
$var wire 8 / alu_result [7:0] $end
$scope module alu $end
$var wire 8 0 A [7:0] $end
$var wire 8 1 B [7:0] $end
$var wire 2 2 opcode [1:0] $end
$var reg 8 3 result [7:0] $end
$upscope $end
$scope module reg_file $end
$var wire 1 $ clk $end
$var wire 3 4 read_addr [2:0] $end
$var wire 3 5 write_addr [2:0] $end
$var wire 8 6 write_data [7:0] $end
$var wire 1 ( write_enable $end
$var reg 8 7 read_data [7:0] $end
$upscope $end
$upscope $end
$upscope $end
$enddefinitions $end
#0
$dumpvars
bx 7
b10001000 6
b0 5
b0 4
b10001000 3
b0 2
b10101010 1
b11001100 0
b10001000 /
bx .
b0 -
b0 ,
b0 +
b10101010 *
b11001100 )
1(
b0 '
b0 &
b0 %
0$
b10101010 #
b11001100 "
bx !
$end
#5
b10001000 !
b10001000 .
b10001000 7
1$
#10
0$
0(
#15
1$
#20
bx !
bx .
bx 7
b11101110 /
b11101110 3
b11101110 6
0$
b1 &
b1 ,
b1 4
1(
b1 '
b1 -
b1 5
b1 %
b1 +
b1 2
#25
b11101110 !
b11101110 .
b11101110 7
1$
#30
0$
0(
#35
1$
#40
bx !
bx .
bx 7
b1110111 /
b1110111 3
b1110111 6
0$
b10 &
b10 ,
b10 4
1(
b10 '
b10 -
b10 5
b10 %
b10 +
b10 2
#45
b1110111 !
b1110111 .
b1110111 7
1$
#50
0$
0(
#55
1$
#60
bx !
bx .
bx 7
b10001 /
b10001 3
b10001 6
0$
b11 &
b11 ,
b11 4
1(
b11 '
b11 -
b11 5
b11 %
b11 +
b11 2
#65
b10001 !
b10001 .
b10001 7
1$
#70
0$
0(
