week 2/simple_circuit1.v
module andgate (y, a, b);  
input a, b;
output y;
assign y = a & b;
endmodule

module orgate (y, a, b);  
input a, b;
output y;
assign y = a | b;
endmodule

module notgate (y, a);  
input a;
output y;
assign y = !a;
endmodule

module simple_circuit1 (A, B, C, D, E);
output D, E;  
input A, B, C;  
wire w1;
andgate G1 (w1, A, B); 
notgate G2 (E, C);    
orgate G3 (D, w1, E); 
endmodule

week 2/simple_circuit1_tb.v
module tb_simple_circuit;
wire D, E;  
reg A, B, C;

simple_circuit1 M1 (.A(A), .B(B), .C(C), .D(D), .E(E));

initial 
begin
#0 A = 1'b0; B = 1'b0; C = 1'b0;
#20 A = 1'b0; B = 1'b0; C = 1'b1;  
#20 A = 1'b0; B = 1'b1; C = 1'b0;
#20 A = 1'b0; B = 1'b1; C = 1'b1;  
#20 A = 1'b1; B = 1'b0; C = 1'b0;  
#20 A = 1'b1; B = 1'b0; C = 1'b1;  
#20 A = 1'b1; B = 1'b1; C = 1'b0;  
#20 A = 1'b1; B = 1'b1; C = 1'b1;  
#20;
end  

initial
begin
$monitor($time," A=%b, B=%b, C=%b, D=%b, E=%b", A, B, C, D, E);
end

initial begin
$dumpfile("simple.vcd");
$dumpvars(1, tb_simple_circuit);  
#200;
$finish;
end
endmodule

week 2/simple.vcd
$date
	Fri Aug 16 14:55:50 2024
$end
$version
	Icarus Verilog
$end
$timescale
	1s
$end
$scope module tb_simple_circuit $end
$var wire 1 ! E $end
$var wire 1 " D $end
$var reg 1 # A $end
$var reg 1 $ B $end
$var reg 1 % C $end
$upscope $end
$enddefinitions $end
#0
$dumpvars
0%
0$
0#
1"
1!
$end
#20
0"
0!
1%
#40
1"
1!
0%
1$
#60
0"
0!
1%
#80
1"
1!
0%
0$
1#
#100
0"
0!
1%
#120
1"
1!
0%
1$
#140
0!
1%
