week 2/simple_circuit3.v
module andgate (y, a, b);  
input a, b;
output y;
assign y = a & b;
endmodule

module orgate (y, a, b);  
input a, b;
output y;
assign y = a | b;
endmodule

module notgate (y, a);  
input a;
output y;
assign y = ~a;
endmodule

module simple_circuit1 (A2, B2, C2, Z);
output Z;  
input A2, B2, C2;  
wire w1, w2, w3;

andgate G1 (w1, C2, B2); 
andgate G2 (w2, B2, A2); 
orgate G3 (w3, w1, A2);
orgate G4 (Z, w3, w2); 

endmodule

week 2/simple_circuit3_tb.v
module tb_simple_circuit;
    wire Z;  
    reg A2, B2, C2;

    simple_circuit1 M1 (.A2(A2), .B2(B2), .C2(C2), .Z(Z));

    initial begin
        A2 = 1'b0; B2 = 1'b0; C2 = 1'b0;
        #20 A2 = 1'b0; B2 = 1'b0; C2 = 1'b1;  
        #20 A2 = 1'b0; B2 = 1'b1; C2 = 1'b0;
        #20 A2 = 1'b0; B2 = 1'b1; C2 = 1'b1;  
        #20 A2 = 1'b1; B2 = 1'b0; C2 = 1'b0;  
        #20 A2 = 1'b1; B2 = 1'b0; C2 = 1'b1;  
        #20 A2 = 1'b1; B2 = 1'b1; C2 = 1'b0;  
        #20 A2 = 1'b1; B2 = 1'b1; C2 = 1'b1;  
        #20;
    end  

    initial begin
        $monitor($time, " A2=%b, B2=%b, C2=%b, Z=%b", A2, B2, C2, Z);
    end

    initial begin
        $dumpfile("simple3.vcd");
        $dumpvars(1, tb_simple_circuit);  
        #200;
        $finish;
    end
endmodule

week 2/simple3.vcd
$date
	Fri Aug 16 15:24:14 2024
$end
$version
	Icarus Verilog
$end
$timescale
	1s
$end
$scope module tb_simple_circuit $end
$var wire 1 ! Z $end
$var reg 1 " A2 $end
$var reg 1 # B2 $end
$var reg 1 $ C2 $end
$upscope $end
$enddefinitions $end
#0
$dumpvars
0$
0#
0"
0!
$end
#20
1$
#40
0$
1#
#60
1!
1$
#80
0$
0#
1"
#100
1$
#120
0$
1#
#140
1$
